Metadata-Version: 2.1
Name: YTClient
Version: 1.0.0
Summary: A rewrite of the YouTrack python API
Home-page: https://github.com/JoshLee0915/youtrack-rest-python-library
Author: Josh Lee
Author-email: 
License: https://github.com/JoshLee0915/youtrack-rest-python-library/blob/master/LICENSE
Platform: UNKNOWN
Requires-Python: >=3.6
